demon_connect/__init__.py
demon_connect/chat/__init__.py
demon_connect/chat/chat.py
demon_connect/chat/conversation.py
demon_connect/chat/group.py
demon_connect/Dockerfile
demon_connect/drivers/chromedriver.exe
demon_connect/drivers/main.txt
demon_connect/features/delete/delete_message.py
demon_connect/features/extras/add_caption.py
demon_connect/features/extras/convert_bytes.py
demon_connect/features/extras/convert_bytes_to.py
demon_connect/features/extras/fetch_all_unread_chats.py
demon_connect/features/extras/find_attachment.py
demon_connect/features/extras/get_list_of_messages.py
demon_connect/features/extras/send_attachment.py
demon_connect/features/login/login_whatsapp.py
demon_connect/features/logout/logout.py
demon_connect/features/send/send_file.py
demon_connect/features/send/send_image.py
demon_connect/features/send/send_message.py
demon_connect/features/send/send_video.py
demon_connect/features/tagall/tagall.py
demon_connect/message/__init__.py
demon_connect/message/message.py
demon_connect/message/unread_message.py
demon_connect/requirements.txt
demon_connect/utils/__init__.py
demon_connect/utils/constants.py
demon_connect/utils/exceptions.py
demon_connect/utils/handler.py
demon_connect/utils/helpers.py
demon_connect/utils/sorce.py
demon_connect/utils/threads.py
demon_connect/whatsapp_api.py
demon_connect-1.0.3.dist-info/LICENSE
demon_connect-1.0.3.dist-info/METADATA
demon_connect-1.0.3.dist-info/WHEEL
demon_connect-1.0.3.dist-info/RECORD
